README.md
setup.py
ankorstore_api_client/__init__.py
ankorstore_api_client/client.py
ankorstore_api_client/resources.py
ankorstore_api_client/utils.py
ankorstore_api_client.egg-info/PKG-INFO
ankorstore_api_client.egg-info/SOURCES.txt
ankorstore_api_client.egg-info/dependency_links.txt
ankorstore_api_client.egg-info/top_level.txt